lyric_py-0.1.7.dist-info/METADATA
lyric_py-0.1.7.dist-info/WHEEL
lyric/config.py
lyric/default_python_worker.py
lyric/driver.py
lyric/py_lyric.py
lyric/task.py
lyric/_py_lyric.pyi
lyric/__init__.py
lyric/_py_lyric.cp310-win_amd64.pyd
lyric_py-0.1.7.dist-info/RECORD
