Metadata-Version: 2.4
Name: lyric-py
Version: 0.1.7
Classifier: Programming Language :: Rust
Classifier: Programming Language :: Python :: Implementation :: CPython
Classifier: Programming Language :: Python :: Implementation :: PyPy
Requires-Dist: msgpack
Requires-Dist: cloudpickle
Requires-Dist: lyric-task
Summary: Python bindings for Lyric: A Rust-powered secure sandbox for multi-language code execution, leveraging WebAssembly to provide high-performance runtime isolation for AI applications
Home-Page: https://github.com/fangyinc/lyric
Author: fangyinc <staneyffer@gmail.com>
Author-email: fangyinc <staneyffer@gmail.com>
License: MIT
Requires-Python: >=3.8
Project-URL: Source Code, https://github.com/fangyinc/lyric
